LICENSE
README.md
setup.py
matprop/__init__.py
matprop/engine.py
matprop/losses.py
matprop/nn.py
matprop.egg-info/PKG-INFO
matprop.egg-info/SOURCES.txt
matprop.egg-info/dependency_links.txt
matprop.egg-info/requires.txt
matprop.egg-info/top_level.txt
test/test_engine.py
test/test_nn.py
test/testing_helpers.py