Metadata-Version: 2.1
Name: matprop
Version: 0.0.1
Summary: A small PyTorch-like backpropagation engine and neural network framework defined with autograd-supported matrix operations
Home-page: https://github.com/danielrjohnson/matprop
Author: Daniel Johnson
Author-email: danielrjohnsonprofessional@gmail.com
License: MIT
Keywords: backpropagation neural network autograd
License-File: LICENSE
